{
  "project_info": {
    "project_number": "646131190495",
    "project_id": "travelnote-79d32",
    "storage_bucket": "travelnote-79d32.firebasestorage.app"
  },
  "client": [
    {
      "client_info": {
        "mobilesdk_app_id": "1:646131190495:android:6afed9bf7bfa5570b6776a",
        "android_client_info": {
          "package_name": "com.example.travelnote"
        }
      },
      "oauth_client": [
        {
          "client_id": "646131190495-f7pend804pig1mr7rtqotkmcus5n90er.apps.googleusercontent.com",
          "client_type": 3
        }
      ],
      "api_key": [
        {
          "current_key": "AIzaSyADtlTcU2OxYHLAXaulG6nOXwpnB5O21-I"
        }
      ],
      "services": {
        "appinvite_service": {
          "other_platform_oauth_client": [
            {
              "client_id": "646131190495-f7pend804pig1mr7rtqotkmcus5n90er.apps.googleusercontent.com",
              "client_type": 3
            },
            {
              "client_id": "646131190495-4ou5uq4qdje933eq4u5o1n0u2m94mk96.apps.googleusercontent.com",
              "client_type": 2,
              "ios_info": {
                "bundle_id": "com.example.travelnote"
              }
            }
          ]
        }
      }
    }
  ],
  "configuration_version": "1"
}